{"cameraMode":{"drawMode":3,"name":"Shadow Cascades","section":"Miscellaneous"},"sceneLighting":true,"audioPlay":false,"sceneViewState":{"m_AlwaysRefresh":false,"showFog":true,"showSkybox":true,"showFlares":true,"showImageEffects":true,"showParticleSystems":true,"showVisualEffectGraphs":true,"m_FxEnabled":true},"in2DMode":false,"pivot":{"x":-84.56566619873047,"y":-146.64031982421876,"z":160.34182739257813},"rotation":{"x":0.32180243730545046,"y":-0.22564604878425599,"z":0.07927122712135315,"w":0.9161080121994019},"size":155.05075073242188,"orthographic":false}